Metadata-Version: 1.0
Name: quantitative
Version: 1.0b0
Summary: Quantitative finance,and back testing library
Home-page: https://github.com/jeffrey-liang/quantitative
Author: Jeffrey Liang
Author-email: jeffrey_liang@sfu.ca
License: Apache 2.0
Keywords: quantitative backtesting finance quant finance stocks
Platform: UNKNOWN
